<?xml version="1.0"?>
<BillOfMaterials Version="1" Minor="2">
  <IPInstance name="SP_Inst_Mem02">
    <FileSets>
      <FileSet generator="apply_current_project_options_generator">
        <File name="./apply_current_project_options_generator.xlog" type="ignore" timestamp="Thu May 22 03:14:45 GMT 2014" checksum="0xFFFFFFFF"></File>
      </FileSet>
      <FileSet generator="model_parameter_resolution_generator">
        <File name="./SP_Inst_Mem02.mif" type="mif" timestamp="Thu May 22 03:13:35 GMT 2014" checksum="0xA899AAA9"></File>
        <File name="./summary.log" type="unknown" timestamp="Thu May 22 03:13:34 GMT 2014" checksum="0x0C6BFA05"></File>
      </FileSet>
      <FileSet generator="ip_xco_generator">
        <File name="./SP_Inst_Mem02.xco" type="xco" timestamp="Thu May 22 03:13:36 GMT 2014" checksum="0x5AB4A88D"></File>
      </FileSet>
      <FileSet generator="associated_files_generator">
        <File name="./SP_Inst_Mem02/blk_mem_gen_v7_3_readme.txt" type="ignore" timestamp="Sun Oct 13 18:11:47 GMT 2013" checksum="0xF95F2A26"></File>
        <File name="./SP_Inst_Mem02/doc/blk_mem_gen_v7_3_vinfo.html" type="ignore" timestamp="Sun Oct 13 18:11:47 GMT 2013" checksum="0x702C7FA8"></File>
        <File name="./SP_Inst_Mem02/doc/pg058-blk-mem-gen.pdf" type="ignore" timestamp="Sun Oct 13 18:11:47 GMT 2013" checksum="0xC1E42F23"></File>
      </FileSet>
      <FileSet generator="ejava_generator">
        <File name="./SP_Inst_Mem02/example_design/SP_Inst_Mem02_exdes.ucf" type="ignore" timestamp="Thu May 22 03:13:36 GMT 2014" checksum="0xC44C6B6D"></File>
        <File name="./SP_Inst_Mem02/example_design/SP_Inst_Mem02_exdes.vhd" type="ignore" timestamp="Thu May 22 03:13:36 GMT 2014" checksum="0x3A67FBE4"></File>
        <File name="./SP_Inst_Mem02/example_design/SP_Inst_Mem02_exdes.xdc" type="ignore" timestamp="Thu May 22 03:13:36 GMT 2014" checksum="0x7684D6D4"></File>
        <File name="./SP_Inst_Mem02/example_design/SP_Inst_Mem02_prod.vhd" type="ignore" timestamp="Thu May 22 03:13:36 GMT 2014" checksum="0xC58833EB"></File>
        <File name="./SP_Inst_Mem02/implement/implement.bat" type="ignore" timestamp="Thu May 22 03:13:36 GMT 2014" checksum="0xFA4333DB"></File>
        <File name="./SP_Inst_Mem02/implement/implement.sh" type="ignore" timestamp="Thu May 22 03:13:36 GMT 2014" checksum="0x1211452C"></File>
        <File name="./SP_Inst_Mem02/implement/planAhead_ise.bat" type="ignore" timestamp="Thu May 22 03:13:36 GMT 2014" checksum="0xECA7AA2B"></File>
        <File name="./SP_Inst_Mem02/implement/planAhead_ise.sh" type="ignore" timestamp="Thu May 22 03:13:36 GMT 2014" checksum="0x707DBE57"></File>
        <File name="./SP_Inst_Mem02/implement/planAhead_ise.tcl" type="ignore" timestamp="Thu May 22 03:13:36 GMT 2014" checksum="0xDF4D2682"></File>
        <File name="./SP_Inst_Mem02/implement/xst.prj" type="ignore" timestamp="Thu May 22 03:13:36 GMT 2014" checksum="0xC6B1A81E"></File>
        <File name="./SP_Inst_Mem02/implement/xst.scr" type="ignore" timestamp="Thu May 22 03:13:36 GMT 2014" checksum="0x06228A96"></File>
        <File name="./SP_Inst_Mem02/simulation/SP_Inst_Mem02_synth.vhd" type="ignore" timestamp="Thu May 22 03:13:36 GMT 2014" checksum="0x39979C6D"></File>
        <File name="./SP_Inst_Mem02/simulation/SP_Inst_Mem02_tb.vhd" type="ignore" timestamp="Thu May 22 03:13:36 GMT 2014" checksum="0x78FEF8B0"></File>
        <File name="./SP_Inst_Mem02/simulation/addr_gen.vhd" type="ignore" timestamp="Thu May 22 03:13:36 GMT 2014" checksum="0x0500E48D"></File>
        <File name="./SP_Inst_Mem02/simulation/bmg_stim_gen.vhd" type="ignore" timestamp="Thu May 22 03:13:36 GMT 2014" checksum="0x03708D7C"></File>
        <File name="./SP_Inst_Mem02/simulation/bmg_tb_pkg.vhd" type="ignore" timestamp="Thu May 22 03:13:36 GMT 2014" checksum="0xE0D93E5B"></File>
        <File name="./SP_Inst_Mem02/simulation/functional/simcmds.tcl" type="ignore" timestamp="Thu May 22 03:13:36 GMT 2014" checksum="0x4E1719BB"></File>
        <File name="./SP_Inst_Mem02/simulation/functional/simulate_isim.bat" type="ignore" timestamp="Thu May 22 03:13:36 GMT 2014" checksum="0x9CEAB645"></File>
        <File name="./SP_Inst_Mem02/simulation/functional/simulate_mti.bat" type="ignore" timestamp="Thu May 22 03:13:36 GMT 2014" checksum="0x86EA5D67"></File>
        <File name="./SP_Inst_Mem02/simulation/functional/simulate_mti.do" type="ignore" timestamp="Thu May 22 03:13:36 GMT 2014" checksum="0x7B25F06D"></File>
        <File name="./SP_Inst_Mem02/simulation/functional/simulate_mti.sh" type="ignore" timestamp="Thu May 22 03:13:36 GMT 2014" checksum="0x86EA5D67"></File>
        <File name="./SP_Inst_Mem02/simulation/functional/simulate_ncsim.sh" type="ignore" timestamp="Thu May 22 03:13:36 GMT 2014" checksum="0x5FF319DE"></File>
        <File name="./SP_Inst_Mem02/simulation/functional/simulate_vcs.sh" type="ignore" timestamp="Thu May 22 03:13:36 GMT 2014" checksum="0x6769D154"></File>
        <File name="./SP_Inst_Mem02/simulation/functional/ucli_commands.key" type="ignore" timestamp="Thu May 22 03:13:36 GMT 2014" checksum="0x9815713F"></File>
        <File name="./SP_Inst_Mem02/simulation/functional/vcs_session.tcl" type="ignore" timestamp="Thu May 22 03:13:36 GMT 2014" checksum="0xCA75BAD5"></File>
        <File name="./SP_Inst_Mem02/simulation/functional/wave_mti.do" type="ignore" timestamp="Thu May 22 03:13:36 GMT 2014" checksum="0x68B71420"></File>
        <File name="./SP_Inst_Mem02/simulation/functional/wave_ncsim.sv" type="ignore" timestamp="Thu May 22 03:13:36 GMT 2014" checksum="0x256F7380"></File>
        <File name="./SP_Inst_Mem02/simulation/random.vhd" type="ignore" timestamp="Thu May 22 03:13:36 GMT 2014" checksum="0x2939160A"></File>
        <File name="./SP_Inst_Mem02/simulation/timing/simcmds.tcl" type="ignore" timestamp="Thu May 22 03:13:36 GMT 2014" checksum="0x4E1719BB"></File>
        <File name="./SP_Inst_Mem02/simulation/timing/simulate_isim.bat" type="ignore" timestamp="Thu May 22 03:13:36 GMT 2014" checksum="0x7327602B"></File>
        <File name="./SP_Inst_Mem02/simulation/timing/simulate_mti.bat" type="ignore" timestamp="Thu May 22 03:13:36 GMT 2014" checksum="0x86EA5D67"></File>
        <File name="./SP_Inst_Mem02/simulation/timing/simulate_mti.do" type="ignore" timestamp="Thu May 22 03:13:36 GMT 2014" checksum="0xC7EC95D8"></File>
        <File name="./SP_Inst_Mem02/simulation/timing/simulate_mti.sh" type="ignore" timestamp="Thu May 22 03:13:36 GMT 2014" checksum="0x86EA5D67"></File>
        <File name="./SP_Inst_Mem02/simulation/timing/simulate_ncsim.sh" type="ignore" timestamp="Thu May 22 03:13:36 GMT 2014" checksum="0xC656D102"></File>
        <File name="./SP_Inst_Mem02/simulation/timing/simulate_vcs.sh" type="ignore" timestamp="Thu May 22 03:13:36 GMT 2014" checksum="0xF762BCD2"></File>
        <File name="./SP_Inst_Mem02/simulation/timing/ucli_commands.key" type="ignore" timestamp="Thu May 22 03:13:36 GMT 2014" checksum="0x9815713F"></File>
        <File name="./SP_Inst_Mem02/simulation/timing/vcs_session.tcl" type="ignore" timestamp="Thu May 22 03:13:36 GMT 2014" checksum="0xA0207F71"></File>
        <File name="./SP_Inst_Mem02/simulation/timing/wave_mti.do" type="ignore" timestamp="Thu May 22 03:13:36 GMT 2014" checksum="0x52990615"></File>
        <File name="./SP_Inst_Mem02/simulation/timing/wave_ncsim.sv" type="ignore" timestamp="Thu May 22 03:13:36 GMT 2014" checksum="0xED02D485"></File>
      </FileSet>
      <FileSet generator="ngc_netlist_generator">
        <File name="./SP_Inst_Mem02.ngc" type="ngc" timestamp="Thu May 22 03:14:30 GMT 2014" checksum="0xCB9623E3"></File>
      </FileSet>
      <FileSet generator="obfuscate_netlist_generator">
        <File name="./obfuscate_netlist_generator.xlog" type="ignore" timestamp="Thu May 22 03:14:45 GMT 2014" checksum="0xFFFFFFFF"></File>
      </FileSet>
      <FileSet generator="padded_implementation_netlist_generator">
        <File name="./padded_implementation_netlist_generator.xlog" type="ignore" timestamp="Thu May 22 03:14:45 GMT 2014" checksum="0xFFFFFFFF"></File>
      </FileSet>
      <FileSet generator="instantiation_template_generator">
        <File name="./SP_Inst_Mem02.veo" type="veo" timestamp="Thu May 22 03:14:31 GMT 2014" checksum="0xFAB80219"></File>
      </FileSet>
      <FileSet generator="structural_simulation_model_generator">
        <File name="./SP_Inst_Mem02.v" type="verilog" timestamp="Thu May 22 03:14:31 GMT 2014" checksum="0xB816ABF0"></File>
      </FileSet>
      <FileSet generator="all_documents_generator">
        <File name="./SP_Inst_Mem02/doc/blk_mem_gen_v7_3_vinfo.html" type="ignore" timestamp="Thu May 22 03:14:31 GMT 2014" checksum="0x702C7FA8"></File>
      </FileSet>
      <FileSet generator="asy_generator">
        <File name="./SP_Inst_Mem02.asy" type="asy" timestamp="Thu May 22 03:14:39 GMT 2014" checksum="0x0FD4F565"></File>
        <File name="./SP_Inst_Mem02.mif" type="mif" timestamp="Thu May 22 03:14:39 GMT 2014" checksum="0xA899AAA9"></File>
        <File name="./summary.log" type="unknown" timestamp="Thu May 22 03:14:37 GMT 2014" checksum="0x0C6BFA05"></File>
      </FileSet>
      <FileSet generator="xmdf_generator">
        <File name="./SP_Inst_Mem02_xmdf.tcl" type="tclXmdf" timestamp="Thu May 22 03:14:39 GMT 2014" checksum="0x5B63409F"></File>
      </FileSet>
      <FileSet generator="synthesis_ise_generator">
        <File name="./SP_Inst_Mem02.gise" type="ignore" timestamp="Thu May 22 03:14:42 GMT 2014" checksum="0xCA91AB5B"></File>
        <File name="./SP_Inst_Mem02.xise" type="ignore" timestamp="Thu May 22 03:14:42 GMT 2014" checksum="0x11EFE0AD"></File>
      </FileSet>
      <FileSet generator="ise_generator">
        <File name="./SP_Inst_Mem02.gise" type="ignore" timestamp="Thu May 22 03:14:45 GMT 2014" checksum="0x98BFD4D8"></File>
        <File name="./SP_Inst_Mem02.xise" type="ignore" timestamp="Thu May 22 03:14:45 GMT 2014" checksum="0x5C876624"></File>
      </FileSet>
      <FileSet generator="deliver_readme_generator">
        <File name="./deliver_readme_generator.xlog" type="ignore" timestamp="Thu May 22 03:14:45 GMT 2014" checksum="0xFFFFFFFF"></File>
      </FileSet>
      <FileSet generator="flist_generator">
        <File name="./SP_Inst_Mem02_flist.txt" type="ignore" timestamp="Thu May 22 03:14:45 GMT 2014" checksum="0xD9FCA891"></File>
      </FileSet>
    </FileSets>
  </IPInstance>
</BillOfMaterials>
